[
  {
    "src": "search",
    "dst": "semantic",
    "weight": 1
  },
  {
    "src": "search",
    "dst": "wolframalpha",
    "weight": 1
  },
  {
    "src": "semantic",
    "dst": "wolframalpha",
    "weight": 1
  },
  {
    "src": "nba",
    "dst": "nbaplayoffs",
    "weight": 1
  },
  {
    "src": "crapvodafonedongle",
    "dst": "itsgrimupnorth",
    "weight": 1
  },
  {
    "src": "tweetie",
    "dst": "twitterfon",
    "weight": 1
  },
  {
    "src": "mdsw",
    "dst": "yarnporn",
    "weight": 1
  },
  {
    "src": "dddscot",
    "dst": "dddsw",
    "weight": 1
  },
  {
    "src": "dddscot",
    "dst": "teched2009",
    "weight": 1
  },
  {
    "src": "dddsw",
    "dst": "teched2009",
    "weight": 1
  },
  {
    "src": "nin",
    "dst": "tampa",
    "weight": 1
  },
  {
    "src": "canucks",
    "dst": "hawks",
    "weight": 1
  },
  {
    "src": "dollhouse",
    "dst": "savedollhouse",
    "weight": 1
  },
  {
    "src": "jtv",
    "dst": "onetvpcdotcom",
    "weight": 1
  },
  {
    "src": "football",
    "dst": "mancity",
    "weight": 1
  },
  {
    "src": "football",
    "dst": "manutd",
    "weight": 1
  },
  {
    "src": "mancity",
    "dst": "manutd",
    "weight": 1
  },
  {
    "src": "f1",
    "dst": "jensonbutton",
    "weight": 1
  },
  {
    "src": "f1",
    "dst": "ruebensbarrichello",
    "weight": 1
  },
  {
    "src": "jensonbutton",
    "dst": "ruebensbarrichello",
    "weight": 1
  },
  {
    "src": "bubble",
    "dst": "twit",
    "weight": 1
  },
  {
    "src": "tag",
    "dst": "tag",
    "weight": 3
  },
  {
    "src": "ershell",
    "dst": "sharepoint",
    "weight": 1
  },
  {
    "src": "ams",
    "dst": "block",
    "weight": 1
  },
  {
    "src": "ams",
    "dst": "wlan",
    "weight": 1
  },
  {
    "src": "block",
    "dst": "wlan",
    "weight": 1
  },
  {
    "src": "rangers",
    "dst": "yankees",
    "weight": 1
  },
  {
    "src": "beer",
    "dst": "cbd",
    "weight": 1
  },
  {
    "src": "beer",
    "dst": "cmon",
    "weight": 1
  },
  {
    "src": "beer",
    "dst": "friday",
    "weight": 1
  },
  {
    "src": "beer",
    "dst": "melbourne",
    "weight": 1
  },
  {
    "src": "beer",
    "dst": "mini",
    "weight": 1
  },
  {
    "src": "beer",
    "dst": "mtub",
    "weight": 1
  },
  {
    "src": "cbd",
    "dst": "cmon",
    "weight": 1
  },
  {
    "src": "cbd",
    "dst": "friday",
    "weight": 1
  },
  {
    "src": "cbd",
    "dst": "melbourne",
    "weight": 1
  },
  {
    "src": "cbd",
    "dst": "mini",
    "weight": 1
  },
  {
    "src": "cbd",
    "dst": "mtub",
    "weight": 1
  },
  {
    "src": "cmon",
    "dst": "friday",
    "weight": 1
  },
  {
    "src": "cmon",
    "dst": "melbourne",
    "weight": 1
  },
  {
    "src": "cmon",
    "dst": "mini",
    "weight": 1
  },
  {
    "src": "cmon",
    "dst": "mtub",
    "weight": 1
  },
  {
    "src": "friday",
    "dst": "melbourne",
    "weight": 1
  },
  {
    "src": "friday",
    "dst": "mini",
    "weight": 1
  },
  {
    "src": "friday",
    "dst": "mtub",
    "weight": 1
  },
  {
    "src": "melbourne",
    "dst": "mini",
    "weight": 1
  },
  {
    "src": "melbourne",
    "dst": "mtub",
    "weight": 1
  },
  {
    "src": "mini",
    "dst": "mtub",
    "weight": 1
  },
  {
    "src": "flyinghussies",
    "dst": "flyinglushes",
    "weight": 2
  },
  {
    "src": "firefox",
    "dst": "wordpress",
    "weight": 1
  },
  {
    "src": "flashcampsf",
    "dst": "flashontap",
    "weight": 1
  },
  {
    "src": "diamond",
    "dst": "fennec",
    "weight": 1
  },
  {
    "src": "diamond",
    "dst": "htc",
    "weight": 1
  },
  {
    "src": "diamond",
    "dst": "mozilla",
    "weight": 1
  },
  {
    "src": "fennec",
    "dst": "htc",
    "weight": 1
  },
  {
    "src": "fennec",
    "dst": "mozilla",
    "weight": 1
  },
  {
    "src": "htc",
    "dst": "mozilla",
    "weight": 1
  },
  {
    "src": "penguins",
    "dst": "rewings",
    "weight": 1
  },
  {
    "src": "pens",
    "dst": "redwings",
    "weight": 2
  },
  {
    "src": "pens",
    "dst": "wings",
    "weight": 1
  },
  {
    "src": "redwings",
    "dst": "redwings",
    "weight": 1
  },
  {
    "src": "redwings",
    "dst": "wings",
    "weight": 2
  },
  {
    "src": "ontd",
    "dst": "ontd",
    "weight": 1
  },
  {
    "src": "ontd",
    "dst": "ontd_startrek",
    "weight": 1
  },
  {
    "src": "andyhurleyday",
    "dst": "andyhurleyday",
    "weight": 28
  },
  {
    "src": "gnutls",
    "dst": "gtalk",
    "weight": 1
  },
  {
    "src": "gnutls",
    "dst": "jabber",
    "weight": 1
  },
  {
    "src": "gnutls",
    "dst": "pidgin",
    "weight": 1
  },
  {
    "src": "gnutls",
    "dst": "xmpp",
    "weight": 1
  },
  {
    "src": "gtalk",
    "dst": "jabber",
    "weight": 1
  },
  {
    "src": "gtalk",
    "dst": "pidgin",
    "weight": 1
  },
  {
    "src": "gtalk",
    "dst": "xmpp",
    "weight": 1
  },
  {
    "src": "jabber",
    "dst": "pidgin",
    "weight": 1
  },
  {
    "src": "jabber",
    "dst": "xmpp",
    "weight": 1
  },
  {
    "src": "pidgin",
    "dst": "xmpp",
    "weight": 1
  },
  {
    "src": "4",
    "dst": "ithwsop",
    "weight": 1
  },
  {
    "src": "clap",
    "dst": "markmartin",
    "weight": 1
  },
  {
    "src": "clap",
    "dst": "nascar",
    "weight": 1
  },
  {
    "src": "markmartin",
    "dst": "nascar",
    "weight": 1
  },
  {
    "src": "cookies",
    "dst": "scrubs",
    "weight": 1
  },
  {
    "src": "fail",
    "dst": "ukweather",
    "weight": 1
  },
  {
    "src": "fail",
    "dst": "fnb",
    "weight": 1
  },
  {
    "src": "lifemojo",
    "dst": "sunfeast10k",
    "weight": 1
  },
  {
    "src": "fakejowhiley",
    "dst": "fakejowhiley",
    "weight": 1
  },
  {
    "src": "iphone",
    "dst": "repair",
    "weight": 1
  },
  {
    "src": "cry",
    "dst": "fail",
    "weight": 1
  },
  {
    "src": "economy",
    "dst": "recession",
    "weight": 1
  },
  {
    "src": "mcflyinmanila",
    "dst": "mcflyinmanila",
    "weight": 1
  },
  {
    "src": "iphone",
    "dst": "rip",
    "weight": 1
  },
  {
    "src": "climate",
    "dst": "nasa",
    "weight": 1
  },
  {
    "src": "facebook",
    "dst": "fail",
    "weight": 1
  },
  {
    "src": "whenisthelosingstreakgonnaend",
    "dst": "whitesox",
    "weight": 1
  },
  {
    "src": "lost",
    "dst": "s1e11",
    "weight": 1
  },
  {
    "src": "lost",
    "dst": "wftb",
    "weight": 1
  },
  {
    "src": "s1e11",
    "dst": "wftb",
    "weight": 1
  },
  {
    "src": "poker",
    "dst": "rakeback",
    "weight": 1
  },
  {
    "src": "f1",
    "dst": "gp",
    "weight": 1
  },
  {
    "src": "pumas",
    "dst": "rugby",
    "weight": 2
  },
  {
    "src": "bfd",
    "dst": "fail",
    "weight": 1
  },
  {
    "src": "spymaster",
    "dst": "zombie",
    "weight": 2
  },
  {
    "src": "nhl",
    "dst": "penguins",
    "weight": 1
  },
  {
    "src": "nhl",
    "dst": "redwings",
    "weight": 1
  },
  {
    "src": "nhl",
    "dst": "redwongs",
    "weight": 1
  },
  {
    "src": "penguins",
    "dst": "redwings",
    "weight": 2
  },
  {
    "src": "penguins",
    "dst": "redwongs",
    "weight": 1
  },
  {
    "src": "redwings",
    "dst": "redwongs",
    "weight": 1
  },
  {
    "src": "cerebralpalsy",
    "dst": "epilepsy",
    "weight": 1
  },
  {
    "src": "cerebralpalsy",
    "dst": "fb",
    "weight": 1
  },
  {
    "src": "cerebralpalsy",
    "dst": "sadhomo",
    "weight": 1
  },
  {
    "src": "cerebralpalsy",
    "dst": "tbi",
    "weight": 1
  },
  {
    "src": "epilepsy",
    "dst": "fb",
    "weight": 1
  },
  {
    "src": "epilepsy",
    "dst": "sadhomo",
    "weight": 1
  },
  {
    "src": "epilepsy",
    "dst": "tbi",
    "weight": 1
  },
  {
    "src": "fb",
    "dst": "sadhomo",
    "weight": 1
  },
  {
    "src": "fb",
    "dst": "tbi",
    "weight": 1
  },
  {
    "src": "sadhomo",
    "dst": "tbi",
    "weight": 1
  },
  {
    "src": "drupal",
    "dst": "sea",
    "weight": 1
  },
  {
    "src": "drupal",
    "dst": "socialmedia",
    "weight": 1
  },
  {
    "src": "sea",
    "dst": "socialmedia",
    "weight": 1
  },
  {
    "src": "f1",
    "dst": "maxout",
    "weight": 1
  },
  {
    "src": "bnp",
    "dst": "eu09",
    "weight": 1
  },
  {
    "src": "golakers",
    "dst": "lakers",
    "weight": 1
  },
  {
    "src": "iranelection",
    "dst": "tehran",
    "weight": 2
  },
  {
    "src": "india",
    "dst": "kolkata",
    "weight": 1
  },
  {
    "src": "primeval",
    "dst": "torchwood",
    "weight": 1
  },
  {
    "src": "squarespace",
    "dst": "squarespace",
    "weight": 2
  },
  {
    "src": "goawaymonday",
    "dst": "tuesdayplz",
    "weight": 1
  },
  {
    "src": "iranelection",
    "dst": "twitterfail",
    "weight": 1
  },
  {
    "src": "kevinjonas",
    "dst": "kevinjonas",
    "weight": 1
  },
  {
    "src": "iran9",
    "dst": "iranelection",
    "weight": 1
  },
  {
    "src": "iran9",
    "dst": "iranians",
    "weight": 1
  },
  {
    "src": "iranelection",
    "dst": "iranians",
    "weight": 1
  },
  {
    "src": "linesvinestryingtimes",
    "dst": "linesvinestryingtimes",
    "weight": 1
  },
  {
    "src": "lions",
    "dst": "rugby",
    "weight": 1
  },
  {
    "src": "lions",
    "dst": "stupidkickofftimes",
    "weight": 1
  },
  {
    "src": "rugby",
    "dst": "stupidkickofftimes",
    "weight": 1
  },
  {
    "src": "lvatt",
    "dst": "lvatt",
    "weight": 21
  },
  {
    "src": "douchebag",
    "dst": "happybirthdaytome",
    "weight": 1
  },
  {
    "src": "140conf",
    "dst": "rayv",
    "weight": 1
  },
  {
    "src": "pweetypweez",
    "dst": "squarespace",
    "weight": 1
  },
  {
    "src": "pweetypweez",
    "dst": "trackle",
    "weight": 1
  },
  {
    "src": "squarespace",
    "dst": "trackle",
    "weight": 5
  },
  {
    "src": "fb",
    "dst": "strohwitwer",
    "weight": 1
  },
  {
    "src": "lwd",
    "dst": "sneakpreview",
    "weight": 1
  },
  {
    "src": "nasa",
    "dst": "shuttle",
    "weight": 1
  },
  {
    "src": "bangalore",
    "dst": "bjp",
    "weight": 1
  },
  {
    "src": "bangalore",
    "dst": "power",
    "weight": 1
  },
  {
    "src": "bjp",
    "dst": "power",
    "weight": 1
  },
  {
    "src": "2",
    "dst": "tweetni",
    "weight": 1
  },
  {
    "src": "masterchef",
    "dst": "spicksandspecks",
    "weight": 1
  },
  {
    "src": "freeze",
    "dst": "salary",
    "weight": 1
  },
  {
    "src": "drupal",
    "dst": "newyork",
    "weight": 1
  },
  {
    "src": "peterfacinelli",
    "dst": "peterfacinelli",
    "weight": 1
  },
  {
    "src": "fixit",
    "dst": "help",
    "weight": 1
  },
  {
    "src": "bottomless",
    "dst": "nanednews",
    "weight": 1
  },
  {
    "src": "fail",
    "dst": "yoono",
    "weight": 1
  },
  {
    "src": "140conf",
    "dst": "followfriday",
    "weight": 1
  },
  {
    "src": "exchange",
    "dst": "technet",
    "weight": 1
  },
  {
    "src": "maeganaguilar",
    "dst": "marcabaya",
    "weight": 1
  },
  {
    "src": "mountainbike",
    "dst": "southafrica",
    "weight": 1
  },
  {
    "src": "davidstea",
    "dst": "fairtrade",
    "weight": 2
  },
  {
    "src": "fairtrade",
    "dst": "fairtrade",
    "weight": 1
  },
  {
    "src": "gr88",
    "dst": "iranelection",
    "weight": 2
  },
  {
    "src": "pre",
    "dst": "pre",
    "weight": 1
  },
  {
    "src": "iran0",
    "dst": "iranelection",
    "weight": 1
  },
  {
    "src": "iran0",
    "dst": "mousavi",
    "weight": 1
  },
  {
    "src": "iran0",
    "dst": "tehran",
    "weight": 1
  },
  {
    "src": "iranelection",
    "dst": "mousavi",
    "weight": 1
  },
  {
    "src": "mousavi",
    "dst": "tehran",
    "weight": 1
  },
  {
    "src": "iran",
    "dst": "zensursula",
    "weight": 1
  },
  {
    "src": "afi",
    "dst": "missmurderer",
    "weight": 1
  },
  {
    "src": "afi",
    "dst": "thesis",
    "weight": 1
  },
  {
    "src": "missmurderer",
    "dst": "thesis",
    "weight": 1
  },
  {
    "src": "btvs",
    "dst": "comicbooks",
    "weight": 1
  },
  {
    "src": "btvs",
    "dst": "georgejeanty",
    "weight": 1
  },
  {
    "src": "comicbooks",
    "dst": "georgejeanty",
    "weight": 1
  },
  {
    "src": "iran",
    "dst": "iranelection",
    "weight": 3
  },
  {
    "src": "bts",
    "dst": "bts",
    "weight": 1
  },
  {
    "src": "onthelow",
    "dst": "onthelow",
    "weight": 1
  },
  {
    "src": "happybdaykrisallen",
    "dst": "happybdaykrisallen",
    "weight": 15
  },
  {
    "src": "iranelection",
    "dst": "neda",
    "weight": 1
  },
  {
    "src": "avatar",
    "dst": "racefail",
    "weight": 1
  },
  {
    "src": "puma",
    "dst": "spyring27",
    "weight": 1
  },
  {
    "src": "puma",
    "dst": "zombieninja",
    "weight": 1
  },
  {
    "src": "spyring27",
    "dst": "zombieninja",
    "weight": 1
  },
  {
    "src": "bpos",
    "dst": "sharepoint",
    "weight": 1
  },
  {
    "src": "football",
    "dst": "spain",
    "weight": 1
  },
  {
    "src": "crochet",
    "dst": "fringe",
    "weight": 1
  },
  {
    "src": "pmot",
    "dst": "webpm",
    "weight": 1
  },
  {
    "src": "blazer",
    "dst": "uprise",
    "weight": 1
  },
  {
    "src": "area51s",
    "dst": "baseball",
    "weight": 1
  },
  {
    "src": "area51s",
    "dst": "vegas",
    "weight": 1
  },
  {
    "src": "baseball",
    "dst": "vegas",
    "weight": 1
  },
  {
    "src": "gnw",
    "dst": "nbn",
    "weight": 1
  },
  {
    "src": "testing",
    "dst": "tweetie",
    "weight": 1
  },
  {
    "src": "nambu",
    "dst": "seesmic",
    "weight": 1
  },
  {
    "src": "nambu",
    "dst": "tweetdeck",
    "weight": 1
  },
  {
    "src": "nambu",
    "dst": "tweetie",
    "weight": 1
  },
  {
    "src": "seesmic",
    "dst": "tweetdeck",
    "weight": 1
  },
  {
    "src": "seesmic",
    "dst": "tweetie",
    "weight": 1
  },
  {
    "src": "tweetdeck",
    "dst": "tweetie",
    "weight": 1
  },
  {
    "src": "hcb",
    "dst": "hhrs",
    "weight": 2
  },
  {
    "src": "hcb",
    "dst": "tcot",
    "weight": 2
  },
  {
    "src": "hhrs",
    "dst": "tcot",
    "weight": 2
  },
  {
    "src": "twitteradio",
    "dst": "twitterradio",
    "weight": 1
  },
  {
    "src": "tibet",
    "dst": "traveler",
    "weight": 1
  },
  {
    "src": "online",
    "dst": "wikileaks",
    "weight": 1
  },
  {
    "src": "followfriday",
    "dst": "payingitforward",
    "weight": 1
  },
  {
    "src": "lichfield",
    "dst": "tweetup",
    "weight": 1
  },
  {
    "src": "h1n1",
    "dst": "swine",
    "weight": 1
  },
  {
    "src": "h1n1",
    "dst": "swineflu",
    "weight": 1
  },
  {
    "src": "swine",
    "dst": "swineflu",
    "weight": 1
  },
  {
    "src": "starwars",
    "dst": "starwarsday",
    "weight": 1
  },
  {
    "src": "boston",
    "dst": "harvard",
    "weight": 1
  },
  {
    "src": "arsenal",
    "dst": "chelsea",
    "weight": 1
  },
  {
    "src": "arsenal",
    "dst": "football",
    "weight": 1
  },
  {
    "src": "chelsea",
    "dst": "football",
    "weight": 1
  },
  {
    "src": "banksy",
    "dst": "coca",
    "weight": 1
  },
  {
    "src": "shortstack",
    "dst": "shortstack",
    "weight": 15
  },
  {
    "src": "shortstack",
    "dst": "tokiohotel",
    "weight": 30
  },
  {
    "src": "tokiohotel",
    "dst": "tokiohotel",
    "weight": 10
  },
  {
    "src": "bellybuttons",
    "dst": "bellybuttons",
    "weight": 28
  },
  {
    "src": "gae",
    "dst": "scala",
    "weight": 1
  },
  {
    "src": "prospective",
    "dst": "usages",
    "weight": 1
  },
  {
    "src": "elevensestime",
    "dst": "letterpress",
    "weight": 1
  },
  {
    "src": "bradiewebb",
    "dst": "bradiewebb",
    "weight": 6
  },
  {
    "src": "bradiewebb",
    "dst": "shaundiviney",
    "weight": 13
  },
  {
    "src": "shaundiviney",
    "dst": "shaundiviney",
    "weight": 3
  },
  {
    "src": "andyclemmensen",
    "dst": "bradiewebb",
    "weight": 1
  },
  {
    "src": "andyclemmensen",
    "dst": "shaundiviney",
    "weight": 1
  },
  {
    "src": "followfriday",
    "dst": "metakong",
    "weight": 1
  },
  {
    "src": "bower",
    "dst": "lichfield",
    "weight": 1
  },
  {
    "src": "followfriday",
    "dst": "media140",
    "weight": 1
  },
  {
    "src": "carpool",
    "dst": "carpool",
    "weight": 1
  },
  {
    "src": "followfriday",
    "dst": "interior",
    "weight": 1
  },
  {
    "src": "ff",
    "dst": "ff",
    "weight": 1
  },
  {
    "src": "followfriday",
    "dst": "funny",
    "weight": 1
  },
  {
    "src": "followfriday",
    "dst": "interesting",
    "weight": 1
  },
  {
    "src": "funny",
    "dst": "interesting",
    "weight": 1
  },
  {
    "src": "ff",
    "dst": "followfriday",
    "weight": 3
  },
  {
    "src": "oewf",
    "dst": "polares",
    "weight": 1
  },
  {
    "src": "add",
    "dst": "adhd",
    "weight": 1
  },
  {
    "src": "add",
    "dst": "asd",
    "weight": 1
  },
  {
    "src": "adhd",
    "dst": "asd",
    "weight": 1
  },
  {
    "src": "directorofphotography",
    "dst": "filmgeek",
    "weight": 1
  },
  {
    "src": "blackradio",
    "dst": "music",
    "weight": 2
  },
  {
    "src": "sotd",
    "dst": "twtfm",
    "weight": 1
  },
  {
    "src": "mallus",
    "dst": "shavam",
    "weight": 1
  },
  {
    "src": "archie",
    "dst": "veronica",
    "weight": 1
  },
  {
    "src": "marsiscoming",
    "dst": "marsiscoming",
    "weight": 18
  },
  {
    "src": "tapas",
    "dst": "victoriarooms",
    "weight": 1
  },
  {
    "src": "mikeywayness",
    "dst": "myweakness",
    "weight": 1
  },
  {
    "src": "education",
    "dst": "methinks",
    "weight": 1
  },
  {
    "src": "education",
    "dst": "opensource",
    "weight": 1
  },
  {
    "src": "education",
    "dst": "potential",
    "weight": 1
  },
  {
    "src": "methinks",
    "dst": "opensource",
    "weight": 1
  },
  {
    "src": "methinks",
    "dst": "potential",
    "weight": 1
  },
  {
    "src": "opensource",
    "dst": "potential",
    "weight": 1
  },
  {
    "src": "digg",
    "dst": "diggshouts",
    "weight": 1
  },
  {
    "src": "followfriday",
    "dst": "followfridaythx",
    "weight": 1
  },
  {
    "src": "votediversity",
    "dst": "votediversity",
    "weight": 28
  },
  {
    "src": "votediversity",
    "dst": "votediversty",
    "weight": 8
  },
  {
    "src": "otalia",
    "dst": "otaliafics",
    "weight": 1
  },
  {
    "src": "5",
    "dst": "kobe",
    "weight": 1
  },
  {
    "src": "5",
    "dst": "lakers",
    "weight": 1
  },
  {
    "src": "kobe",
    "dst": "lakers",
    "weight": 1
  },
  {
    "src": "chesterday",
    "dst": "chesterday",
    "weight": 6
  },
  {
    "src": "geburt",
    "dst": "scohrid",
    "weight": 1
  },
  {
    "src": "geburt",
    "dst": "telss09",
    "weight": 1
  },
  {
    "src": "geburt",
    "dst": "wedotel",
    "weight": 1
  },
  {
    "src": "scohrid",
    "dst": "telss09",
    "weight": 1
  },
  {
    "src": "scohrid",
    "dst": "wedotel",
    "weight": 1
  },
  {
    "src": "telss09",
    "dst": "wedotel",
    "weight": 1
  },
  {
    "src": "friend",
    "dst": "hugs",
    "weight": 1
  },
  {
    "src": "iswearididntlearnthisatall",
    "dst": "s2istheworst4chaptertextbookever",
    "weight": 1
  },
  {
    "src": "iswearididntlearnthisatall",
    "dst": "skylarksandsquirrels",
    "weight": 1
  },
  {
    "src": "s2istheworst4chaptertextbookever",
    "dst": "skylarksandsquirrels",
    "weight": 1
  },
  {
    "src": "innerlesbo",
    "dst": "shameless",
    "weight": 1
  },
  {
    "src": "innerlesbo",
    "dst": "yumyum",
    "weight": 1
  },
  {
    "src": "shameless",
    "dst": "yumyum",
    "weight": 1
  },
  {
    "src": "cars",
    "dst": "cgi",
    "weight": 1
  },
  {
    "src": "cars",
    "dst": "pixar",
    "weight": 1
  },
  {
    "src": "cgi",
    "dst": "pixar",
    "weight": 1
  },
  {
    "src": "miguelrequests",
    "dst": "miguelrequests",
    "weight": 6
  },
  {
    "src": "bing",
    "dst": "microsoft",
    "weight": 1
  },
  {
    "src": "mullenchardonnay",
    "dst": "mulleninteractive",
    "weight": 1
  },
  {
    "src": "mullenchardonnay",
    "dst": "mullenunbound",
    "weight": 1
  },
  {
    "src": "mulleninteractive",
    "dst": "mullenunbound",
    "weight": 1
  },
  {
    "src": "mileymonday",
    "dst": "mileymonday",
    "weight": 45
  },
  {
    "src": "chuckmemonday",
    "dst": "chuckmeweek",
    "weight": 1
  },
  {
    "src": "photog",
    "dst": "togsfollow",
    "weight": 1
  },
  {
    "src": "naples",
    "dst": "rome",
    "weight": 1
  },
  {
    "src": "1",
    "dst": "2",
    "weight": 2
  },
  {
    "src": "chuckeu",
    "dst": "chuckmemondays",
    "weight": 2
  },
  {
    "src": "e3",
    "dst": "starwars",
    "weight": 1
  },
  {
    "src": "funny",
    "dst": "win7",
    "weight": 1
  },
  {
    "src": "chuck",
    "dst": "chuckmemondays",
    "weight": 2
  },
  {
    "src": "web",
    "dst": "yeg",
    "weight": 1
  },
  {
    "src": "myspace",
    "dst": "retarded",
    "weight": 1
  },
  {
    "src": "cult",
    "dst": "girlfriend",
    "weight": 1
  },
  {
    "src": "cult",
    "dst": "mortgage",
    "weight": 1
  },
  {
    "src": "girlfriend",
    "dst": "mortgage",
    "weight": 1
  },
  {
    "src": "kde",
    "dst": "mallu",
    "weight": 1
  },
  {
    "src": "kde",
    "dst": "panvel",
    "weight": 1
  },
  {
    "src": "mallu",
    "dst": "panvel",
    "weight": 1
  },
  {
    "src": "eclipse",
    "dst": "netbeans",
    "weight": 1
  },
  {
    "src": "egypt",
    "dst": "obama",
    "weight": 1
  },
  {
    "src": "happy",
    "dst": "metapeople",
    "weight": 1
  },
  {
    "src": "origin",
    "dst": "soo",
    "weight": 1
  },
  {
    "src": "alltimelow",
    "dst": "alltimelow",
    "weight": 64
  },
  {
    "src": "followfriday",
    "dst": "followfriday",
    "weight": 1
  },
  {
    "src": "seb",
    "dst": "seb",
    "weight": 210
  },
  {
    "src": "mlb",
    "dst": "nascar",
    "weight": 1
  },
  {
    "src": "mlb",
    "dst": "phillies",
    "weight": 1
  },
  {
    "src": "mlb",
    "dst": "trucks",
    "weight": 1
  },
  {
    "src": "nascar",
    "dst": "phillies",
    "weight": 1
  },
  {
    "src": "nascar",
    "dst": "trucks",
    "weight": 1
  },
  {
    "src": "phillies",
    "dst": "trucks",
    "weight": 1
  },
  {
    "src": "nascar",
    "dst": "truckseries",
    "weight": 1
  },
  {
    "src": "followfriday",
    "dst": "video",
    "weight": 1
  },
  {
    "src": "berlin",
    "dst": "weather",
    "weight": 1
  },
  {
    "src": "berlin",
    "dst": "wetter",
    "weight": 1
  },
  {
    "src": "weather",
    "dst": "wetter",
    "weight": 1
  },
  {
    "src": "itunes",
    "dst": "pre",
    "weight": 1
  },
  {
    "src": "friendly",
    "dst": "sincere",
    "weight": 1
  },
  {
    "src": "mssucks",
    "dst": "multiplesclerosis",
    "weight": 1
  },
  {
    "src": "mssucks",
    "dst": "multscler",
    "weight": 1
  },
  {
    "src": "multiplesclerosis",
    "dst": "multscler",
    "weight": 1
  },
  {
    "src": "e2ct",
    "dst": "twtvite",
    "weight": 1
  },
  {
    "src": "fashion",
    "dst": "fashion",
    "weight": 1
  },
  {
    "src": "noonefuckswithjakksinboston",
    "dst": "oldportfest",
    "weight": 1
  },
  {
    "src": "lakers",
    "dst": "magic",
    "weight": 1
  },
  {
    "src": "lakers",
    "dst": "penguins",
    "weight": 1
  },
  {
    "src": "lakers",
    "dst": "redwings",
    "weight": 1
  },
  {
    "src": "magic",
    "dst": "penguins",
    "weight": 1
  },
  {
    "src": "magic",
    "dst": "redwings",
    "weight": 1
  },
  {
    "src": "cnnfail",
    "dst": "iranelection",
    "weight": 1
  },
  {
    "src": "dl4sg",
    "dst": "sg4dl",
    "weight": 1
  },
  {
    "src": "obsessed",
    "dst": "obsessed",
    "weight": 1
  },
  {
    "src": "boston",
    "dst": "digg",
    "weight": 1
  },
  {
    "src": "boston",
    "dst": "nice",
    "weight": 1
  },
  {
    "src": "boston",
    "dst": "notes",
    "weight": 1
  },
  {
    "src": "digg",
    "dst": "nice",
    "weight": 1
  },
  {
    "src": "digg",
    "dst": "notes",
    "weight": 1
  },
  {
    "src": "nice",
    "dst": "notes",
    "weight": 1
  },
  {
    "src": "sfo",
    "dst": "sgs09",
    "weight": 1
  },
  {
    "src": "iranelection",
    "dst": "iremember",
    "weight": 1
  },
  {
    "src": "bb10",
    "dst": "squarespace",
    "weight": 1
  },
  {
    "src": "hd67",
    "dst": "saci",
    "weight": 1
  },
  {
    "src": "lvatt",
    "dst": "musicmonday",
    "weight": 1
  },
  {
    "src": "gift",
    "dst": "golf",
    "weight": 1
  },
  {
    "src": "cpanel",
    "dst": "rails",
    "weight": 1
  },
  {
    "src": "dnn",
    "dst": "dnnvoice",
    "weight": 1
  },
  {
    "src": "dnn",
    "dst": "dodnn",
    "weight": 1
  },
  {
    "src": "dnnvoice",
    "dst": "dodnn",
    "weight": 1
  },
  {
    "src": "byranflurry",
    "dst": "notoconass",
    "weight": 1
  },
  {
    "src": "linux",
    "dst": "solaris",
    "weight": 1
  },
  {
    "src": "linux",
    "dst": "windows",
    "weight": 1
  },
  {
    "src": "solaris",
    "dst": "windows",
    "weight": 1
  },
  {
    "src": "awesomeness",
    "dst": "experiment",
    "weight": 1
  },
  {
    "src": "awesomeness",
    "dst": "ftw",
    "weight": 1
  },
  {
    "src": "experiment",
    "dst": "ftw",
    "weight": 1
  },
  {
    "src": "freehouse",
    "dst": "pixelmytwitter",
    "weight": 1
  },
  {
    "src": "fb",
    "dst": "formula1",
    "weight": 1
  },
  {
    "src": "fb",
    "dst": "nurburgring",
    "weight": 1
  },
  {
    "src": "fb",
    "dst": "sounddesign",
    "weight": 1
  },
  {
    "src": "formula1",
    "dst": "nurburgring",
    "weight": 1
  },
  {
    "src": "formula1",
    "dst": "sounddesign",
    "weight": 1
  },
  {
    "src": "nurburgring",
    "dst": "sounddesign",
    "weight": 1
  },
  {
    "src": "3",
    "dst": "4",
    "weight": 1
  },
  {
    "src": "php",
    "dst": "zf",
    "weight": 1
  }
]